CHANGES
COPYING
MANIFEST.in
README.rst
setup.py
example/__init__.py
example/dosomething.py
example/registries.py
example/app1/__init__.py
example/app1/callbacks_registry.py
example/app2/__init__.py
example/app2/callbacks_registry.py
persisting_theory/__init__.py
persisting_theory/registries.py
persisting_theory.egg-info/PKG-INFO
persisting_theory.egg-info/SOURCES.txt
persisting_theory.egg-info/dependency_links.txt
persisting_theory.egg-info/not-zip-safe
persisting_theory.egg-info/top_level.txt
tests/__init__.py
tests/test_registries.py
tests/tests.py
tests/app1/__init__.py
tests/app1/awesome_people.py
tests/app1/vegetables.py
tests/app2/__init__.py
tests/app2/awesome_people.py
tests/app2/vegetables.py
tests/buggy_app/__init__.py
tests/buggy_app/awesome_people.py