Metadata-Version: 1.1
Name: persisting-theory
Version: 0.2.1
Summary: Registries that can autodiscover values accross your project apps
Home-page: http://code.eliotberriot.com/eliotberriot/persisting-theory
Author: Eliot Berriot
Author-email: contact@eliotberriot.com
License: BSD
Platform: UNKNOWN
Classifier: Intended Audience :: Developers
Classifier: License :: OSI Approved :: BSD License
Classifier: Operating System :: OS Independent
Classifier: Programming Language :: Python
Classifier: Programming Language :: Python :: 2.7
Classifier: Programming Language :: Python :: 3.4
